flexpolyline/__init__.py
flexpolyline/decoding.py
flexpolyline/encoding.py
flexpolyline-0.1.0.dist-info/LICENSE
flexpolyline-0.1.0.dist-info/METADATA
flexpolyline-0.1.0.dist-info/WHEEL
flexpolyline-0.1.0.dist-info/top_level.txt
flexpolyline-0.1.0.dist-info/RECORD
