Metadata-Version: 2.1
Name: flexpolyline
Version: 0.1.0
Summary: Flexible Polyline encoding: a lossy compressed representation of a list of coordinate pairs or triples
Home-page: https://here.com
Author: HERE Europe B.V.
License: MIT
Project-URL: Source, https://github.com/heremaps/flexible-polyline.git
Platform: UNKNOWN
Classifier: Intended Audience :: Developers
Classifier: Programming Language :: Python :: 2.7
Classifier: Programming Language :: Python :: 3.6
Classifier: Programming Language :: Python :: 3.7
Classifier: License :: OSI Approved :: MIT License
